mydlib/__init__.py
mydlib/libgenget.py
mydlib/mydlib.py
mydlib/traverser.py
mydlib-0.3.dist-info/METADATA
mydlib-0.3.dist-info/WHEEL
mydlib-0.3.dist-info/top_level.txt
mydlib-0.3.dist-info/RECORD
