Metadata-Version: 2.1
Name: mydlib
Version: 0.3
Summary: A library (books) creator and simple libgen book downloader.
Home-page: https://github.com/anuragmaurya/mydlib
Author: Anurag Maurya
Author-email: anumaurya114@gmail.com
License: UNKNOWN
Platform: UNKNOWN
Classifier: Programming Language :: Python :: 3
Classifier: License :: OSI Approved :: MIT License
